mysociety_django_pipeline_compass_rubygem-0.1.8.1.dist-info/DESCRIPTION.rst
mysociety_django_pipeline_compass_rubygem-0.1.8.1.dist-info/METADATA
mysociety_django_pipeline_compass_rubygem-0.1.8.1.dist-info/metadata.json
mysociety_django_pipeline_compass_rubygem-0.1.8.1.dist-info/RECORD
mysociety_django_pipeline_compass_rubygem-0.1.8.1.dist-info/top_level.txt
mysociety_django_pipeline_compass_rubygem-0.1.8.1.dist-info/WHEEL
pipeline_compass/__init__.py
pipeline_compass/compass.py
