Metadata-Version: 2.0
Name: mysociety-django-pipeline-compass-rubygem
Version: 0.1.8.1
Summary: 
